oauth_middleware/__init__.py
oauth_middleware/_version.py
oauth_middleware/middleware.py
oauth_middleware/providers/__init__.py
oauth_middleware/providers/zalando.py
oauth_middleware-0.3.3.dist-info/DESCRIPTION.rst
oauth_middleware-0.3.3.dist-info/METADATA
oauth_middleware-0.3.3.dist-info/RECORD
oauth_middleware-0.3.3.dist-info/WHEEL
oauth_middleware-0.3.3.dist-info/metadata.json
oauth_middleware-0.3.3.dist-info/top_level.txt
