Metadata-Version: 2.0
Name: oauth-middleware
Version: 0.3.3
Summary: Simple flask_oauthlib based middleware for WSGI app to preform oauth
Home-page: https://github.com/last-g/oauth_middleware
Author: Last G
Author-email: sergei.azovskov@zalando.de
License: UNKNOWN
Platform: UNKNOWN
Classifier: Development Status :: 3 - Alpha
Classifier: Intended Audience :: Developers
Classifier: License :: OSI Approved :: MIT License
Classifier: Operating System :: OS Independent
Classifier: Programming Language :: Python :: 2.7
Classifier: Programming Language :: Python :: 3
Classifier: Programming Language :: Python :: 3.3
Classifier: Programming Language :: Python :: 3.4
Classifier: Programming Language :: Python :: 3.5
Classifier: Topic :: Software Development :: Libraries :: Python Modules
Classifier: Topic :: Internet :: WWW/HTTP :: WSGI :: Middleware
Requires-Dist: flask
Requires-Dist: flask-oauthlib
Requires-Dist: six
Requires-Dist: werkzeug
